<?xml version="1.0" encoding="UTF-8"?>
<objects serializationModel="Studio.02.00.00">
	<object class="EncodingSetting" id="{e6d8fefb-f816-455f-a7fd-8755f1c5e0c6}">
		<property name="encodingFormat">
			<value>3</value>
		</property>
		<property name="quality">
			<value>37</value>
		</property>
		<relationship name="platform">
			<destination>{a56718a1-0f5b-4fb8-bafc-b28be21c75cc}</destination>
		</relationship>
		<relationship name="encodable">
			<destination>{a56718a1-0f5b-4fb8-bafc-b28be21c75cc}</destination>
		</relationship>
	</object>
</objects>
